tiger_eval/__init__.py
tiger_eval/__main__.py
tiger_eval/config.toml
tiger_eval/cross_lingual_assessment.py
tiger_eval/multichoice_align.py
tiger_eval/multichoice_question.py
tiger_eval/open_question_model_judge.py
tiger_eval/rouge.py
tiger_eval/translation_bleu.py
tiger_eval-0.0.2.dist-info/LICENSE
tiger_eval-0.0.2.dist-info/METADATA
tiger_eval-0.0.2.dist-info/WHEEL
tiger_eval-0.0.2.dist-info/entry_points.txt
tiger_eval-0.0.2.dist-info/top_level.txt
tiger_eval-0.0.2.dist-info/RECORD
