Metadata-Version: 2.1
Name: tiger-eval
Version: 0.0.2
Summary: Text Generation Evaluation Toolkit
Author: Bin Wang, Zhengyuan Liu, Geyu Lin
License: Apache License
Project-URL: repository, https://github.com/SeaEval/TiGEr_Eval
Project-URL: documentation, https://github.com/SeaEval/TiGEr_Eval
Keywords: evaluation,text,generation
Classifier: License :: OSI Approved :: Apache Software License
Classifier: Programming Language :: Python
Classifier: Programming Language :: Python :: 3
Requires-Python: >=3.7
License-File: LICENSE
Requires-Dist: feedparser
Requires-Dist: html2text
Requires-Dist: rouge-score
Requires-Dist: tomli ; python_version < "3.11"
Provides-Extra: build
Requires-Dist: build ; extra == 'build'
Requires-Dist: twine ; extra == 'build'
Provides-Extra: dev
Requires-Dist: black ; extra == 'dev'
Requires-Dist: bumpver ; extra == 'dev'
Requires-Dist: isort ; extra == 'dev'
Requires-Dist: mypy ; extra == 'dev'
Requires-Dist: pytest ; extra == 'dev'
